{
  "project_info": {
    "project_number": "358729633681",
    "project_id": "waroforigin",
    "storage_bucket": "waroforigin.appspot.com"
  },
  "client": [
    {
      "client_info": {
        "mobilesdk_app_id": "1:358729633681:android:d31f6e27cde64b6e5dd430",
        "android_client_info": {
          "package_name": "com.mjcompany.waroforigin"
        }
      },
      "oauth_client": [
        {
          "client_id": "358729633681-mv24rdicc3hvff9k865vrbsp9s2eehcq.apps.googleusercontent.com",
          "client_type": 3
        }
      ],
      "api_key": [
        {
          "current_key": "AIzaSyA0nPlLhuJoWSL3VsJOS_8TQRoRUo6zhzQ"
        }
      ],
      "services": {
        "appinvite_service": {
          "other_platform_oauth_client": [
            {
              "client_id": "358729633681-mv24rdicc3hvff9k865vrbsp9s2eehcq.apps.googleusercontent.com",
              "client_type": 3
            }
          ]
        }
      }
    }
  ],
  "configuration_version": "1"
}